{
  "DataEntityMetadataJson": {
    "b6645f33-1a17-4858-9c14-16cc8efe49df": "{\"name\":\"b6645f33-1a17-4858-9c14-16cc8efe49df\",\"title\":\"InventarioMantenimientoCilindros\",\"x-ms-permission\":\"read-write\",\"x-ms-capabilities\":{\"sortRestrictions\":{\"sortable\":true,\"unsortableProperties\":[\"{Identifier}\",\"{IsFolder}\",\"{Thumbnail}\",\"{Link}\",\"{Name}\",\"{FilenameWithExtension}\",\"{Path}\",\"{FullPath}\",\"{ModerationStatus}\",\"{ModerationComment}\",\"{ContentType}\",\"{HasAttachments}\",\"{Attachments}\",\"{VersionNumber}\",\"{TriggerWindowStartToken}\",\"{TriggerWindowEndToken}\"]},\"filterRestrictions\":{\"filterable\":true,\"nonFilterableProperties\":[\"{Identifier}\",\"{IsFolder}\",\"{Thumbnail}\",\"{Link}\",\"{Name}\",\"{FilenameWithExtension}\",\"{Path}\",\"{FullPath}\",\"{ModerationStatus}\",\"{ModerationComment}\",\"{ContentType}\",\"{HasAttachments}\",\"{Attachments}\",\"{VersionNumber}\",\"{TriggerWindowStartToken}\",\"{TriggerWindowEndToken}\"]},\"isOnlyServerPagable\":true,\"filterFunctionSupport\":[\"and\",\"or\",\"eq\",\"startswith\",\"gt\",\"ge\",\"lt\",\"le\",\"ne\"],\"serverPagingOptions\":[\"top\",\"skiptoken\"],\"odataVersion\":3},\"schema\":{\"type\":\"array\",\"items\":{\"type\":\"object\",\"required\":[\"Cargo\",\"CENTROOPERACION\",\"FechaCreacion\",\"CilindrosLavados\",\"Cantidad\",\"Turno\"],\"properties\":{\"ID\":{\"title\":\"ID\",\"description\":\"Id. de elemento de lista. Utilice este valor para especificar el elemento que actúa en otra lista de acciones relacionadas.\",\"type\":\"integer\",\"format\":\"int64\",\"x-ms-keyType\":\"primary\",\"x-ms-keyOrder\":1,\"x-ms-permission\":\"read-only\",\"x-ms-sort\":\"asc,desc\",\"x-ms-capabilities\":{\"filterFunctions\":[\"eq\"]}},\"Title\":{\"title\":\"0\",\"type\":\"string\",\"x-ms-permission\":\"read-write\",\"x-ms-sort\":\"asc,desc\",\"x-ms-capabilities\":{\"filterFunctions\":[\"eq\",\"startswith\"]},\"maxLength\":255},\"Registr_x00f3__x003a_#Id\":{\"title\":\"Realiza Registro Id\",\"type\":\"integer\",\"format\":\"int64\",\"x-ms-permission\":\"read-only\",\"x-ms-visibility\":\"internal\"},\"Registr_x00f3__x003a_\":{\"title\":\"Realiza Registro\",\"type\":\"object\",\"x-ms-permission\":\"read-write\",\"x-ms-sort\":\"asc,desc\",\"x-ms-capabilities\":{\"x-ms-sp\":{\"IsChoice\":true},\"filterFunctions\":[\"eq\"]},\"properties\":{\"@odata.type\":{\"title\":\"@odata.type\",\"x-ms-visibility\":\"internal\",\"type\":\"string\",\"x-ms-permission\":\"read-write\"},\"Value\":{\"title\":\"Value\",\"type\":\"string\",\"x-ms-dynamic-values\":{\"operationId\":\"GetEntityValues\",\"parameters\":{\"dataset\":{\"parameter\":\"dataset\"},\"table\":{\"parameter\":\"table\"},\"id\":\"66389dcb-8441-4fe6-a4cd-fb1cfbcd18e7\"},\"value-path\":\"Value\",\"value-title\":\"Value\",\"value-collection\":\"value\"}},\"Id\":{\"title\":\"Id\",\"type\":\"integer\",\"format\":\"int64\",\"x-ms-visibility\":\"internal\",\"x-ms-permission\":\"read-only\"}},\"x-ms-displayFormat\":{\"titleProperty\":\"Value\"}},\"Cargo#Id\":{\"title\":\"Cargo Id\",\"type\":\"integer\",\"format\":\"int64\",\"x-ms-permission\":\"read-only\",\"x-ms-visibility\":\"internal\"},\"Cargo\":{\"title\":\"Cargo\",\"type\":\"object\",\"x-ms-permission\":\"read-write\",\"x-ms-sort\":\"asc,desc\",\"x-ms-capabilities\":{\"x-ms-sp\":{\"IsChoice\":true},\"filterFunctions\":[\"eq\"]},\"properties\":{\"@odata.type\":{\"title\":\"@odata.type\",\"x-ms-visibility\":\"internal\",\"type\":\"string\",\"x-ms-permission\":\"read-write\"},\"Value\":{\"title\":\"Value\",\"type\":\"string\",\"x-ms-dynamic-values\":{\"operationId\":\"GetEntityValues\",\"parameters\":{\"dataset\":{\"parameter\":\"dataset\"},\"table\":{\"parameter\":\"table\"},\"id\":\"443949ff-82ba-45f9-b4dc-865329bb40d1\"},\"value-path\":\"Value\",\"value-title\":\"Value\",\"value-collection\":\"value\"}},\"Id\":{\"title\":\"Id\",\"type\":\"integer\",\"format\":\"int64\",\"x-ms-visibility\":\"internal\",\"x-ms-permission\":\"read-only\"}},\"x-ms-displayFormat\":{\"titleProperty\":\"Value\"}},\"CENTROOPERACION#Id\":{\"title\":\"Centro Operacion Id\",\"type\":\"integer\",\"format\":\"int64\",\"x-ms-permission\":\"read-only\",\"x-ms-visibility\":\"internal\"},\"CENTROOPERACION\":{\"title\":\"Centro Operacion\",\"type\":\"object\",\"x-ms-permission\":\"read-write\",\"x-ms-sort\":\"asc,desc\",\"x-ms-capabilities\":{\"x-ms-sp\":{\"IsChoice\":true},\"filterFunctions\":[\"eq\"]},\"properties\":{\"@odata.type\":{\"title\":\"@odata.type\",\"x-ms-visibility\":\"internal\",\"type\":\"string\",\"x-ms-permission\":\"read-write\"},\"Value\":{\"title\":\"Value\",\"type\":\"string\",\"x-ms-dynamic-values\":{\"operationId\":\"GetEntityValues\",\"parameters\":{\"dataset\":{\"parameter\":\"dataset\"},\"table\":{\"parameter\":\"table\"},\"id\":\"3ca25d3a-3231-4eb3-b397-c45923bfd71a\"},\"value-path\":\"Value\",\"value-title\":\"Value\",\"value-collection\":\"value\"}},\"Id\":{\"title\":\"Id\",\"type\":\"integer\",\"format\":\"int64\",\"x-ms-visibility\":\"internal\",\"x-ms-permission\":\"read-only\"}},\"x-ms-displayFormat\":{\"titleProperty\":\"Value\"}},\"FechaCreacion\":{\"title\":\"Fecha Creación\",\"type\":\"string\",\"format\":\"date\",\"x-ms-permission\":\"read-write\",\"x-ms-sort\":\"asc,desc\",\"x-ms-capabilities\":{\"filterFunctions\":[\"eq\",\"gt\",\"ge\",\"lt\",\"le\",\"ne\"]}},\"CilindrosLavados#Id\":{\"title\":\"Cilindros Lavados (1) Id\",\"type\":\"integer\",\"format\":\"int64\",\"x-ms-permission\":\"read-only\",\"x-ms-visibility\":\"internal\"},\"CilindrosLavados\":{\"title\":\"Cilindros Lavados (1)\",\"type\":\"object\",\"x-ms-permission\":\"read-write\",\"x-ms-sort\":\"asc,desc\",\"x-ms-capabilities\":{\"x-ms-sp\":{\"IsChoice\":true},\"filterFunctions\":[\"eq\"]},\"properties\":{\"@odata.type\":{\"title\":\"@odata.type\",\"x-ms-visibility\":\"internal\",\"type\":\"string\",\"x-ms-permission\":\"read-write\"},\"Value\":{\"title\":\"Value\",\"type\":\"string\",\"x-ms-dynamic-values\":{\"operationId\":\"GetEntityValues\",\"parameters\":{\"dataset\":{\"parameter\":\"dataset\"},\"table\":{\"parameter\":\"table\"},\"id\":\"6bfb0269-67a6-49e9-a213-c767fcef6ec8\"},\"value-path\":\"Value\",\"value-title\":\"Value\",\"value-collection\":\"value\"}},\"Id\":{\"title\":\"Id\",\"type\":\"integer\",\"format\":\"int64\",\"x-ms-visibility\":\"internal\",\"x-ms-permission\":\"read-only\"}},\"x-ms-displayFormat\":{\"titleProperty\":\"Value\"}},\"Cantidad\":{\"title\":\"Cantidad (1)\",\"description\":\"Debe ingresar la cantidad a los cuales se les realizo el mantenimiento de lavado o pintado.\",\"type\":\"number\",\"format\":\"double\",\"x-ms-permission\":\"read-write\",\"x-ms-sort\":\"asc,desc\",\"x-ms-capabilities\":{\"filterFunctions\":[\"eq\",\"gt\",\"ge\",\"lt\",\"le\",\"ne\"]},\"maximum\":500,\"minimum\":-1.7976931348623157e+308},\"CilindrosLavados2#Id\":{\"title\":\"Cilindros Lavados (2) Id\",\"type\":\"integer\",\"format\":\"int64\",\"x-ms-permission\":\"read-only\",\"x-ms-visibility\":\"internal\"},\"CilindrosLavados2\":{\"title\":\"Cilindros Lavados (2)\",\"type\":\"object\",\"x-ms-permission\":\"read-write\",\"x-ms-sort\":\"asc,desc\",\"x-ms-capabilities\":{\"x-ms-sp\":{\"IsChoice\":true},\"filterFunctions\":[\"eq\"]},\"properties\":{\"@odata.type\":{\"title\":\"@odata.type\",\"x-ms-visibility\":\"internal\",\"type\":\"string\",\"x-ms-permission\":\"read-write\"},\"Value\":{\"title\":\"Value\",\"type\":\"string\",\"x-ms-dynamic-values\":{\"operationId\":\"GetEntityValues\",\"parameters\":{\"dataset\":{\"parameter\":\"dataset\"},\"table\":{\"parameter\":\"table\"},\"id\":\"dd61be47-c274-406e-943c-291759732d09\"},\"value-path\":\"Value\",\"value-title\":\"Value\",\"value-collection\":\"value\"}},\"Id\":{\"title\":\"Id\",\"type\":\"integer\",\"format\":\"int64\",\"x-ms-visibility\":\"internal\",\"x-ms-permission\":\"read-only\"}},\"x-ms-displayFormat\":{\"titleProperty\":\"Value\"}},\"Cantidad2\":{\"title\":\"Cantidad (2)\",\"type\":\"number\",\"format\":\"double\",\"x-ms-permission\":\"read-write\",\"x-ms-sort\":\"asc,desc\",\"x-ms-capabilities\":{\"filterFunctions\":[\"eq\",\"gt\",\"ge\",\"lt\",\"le\",\"ne\"]},\"maximum\":1.7976931348623157e+308,\"minimum\":-1.7976931348623157e+308},\"Cilindroslavados3#Id\":{\"title\":\"Cilindros lavados (3) Id\",\"type\":\"integer\",\"format\":\"int64\",\"x-ms-permission\":\"read-only\",\"x-ms-visibility\":\"internal\"},\"Cilindroslavados3\":{\"title\":\"Cilindros lavados (3)\",\"type\":\"object\",\"x-ms-permission\":\"read-write\",\"x-ms-sort\":\"asc,desc\",\"x-ms-capabilities\":{\"x-ms-sp\":{\"IsChoice\":true},\"filterFunctions\":[\"eq\"]},\"properties\":{\"@odata.type\":{\"title\":\"@odata.type\",\"x-ms-visibility\":\"internal\",\"type\":\"string\",\"x-ms-permission\":\"read-write\"},\"Value\":{\"title\":\"Value\",\"type\":\"string\",\"x-ms-dynamic-values\":{\"operationId\":\"GetEntityValues\",\"parameters\":{\"dataset\":{\"parameter\":\"dataset\"},\"table\":{\"parameter\":\"table\"},\"id\":\"2a44fc9d-bb3d-466f-957a-7fff6921ba46\"},\"value-path\":\"Value\",\"value-title\":\"Value\",\"value-collection\":\"value\"}},\"Id\":{\"title\":\"Id\",\"type\":\"integer\",\"format\":\"int64\",\"x-ms-visibility\":\"internal\",\"x-ms-permission\":\"read-only\"}},\"x-ms-displayFormat\":{\"titleProperty\":\"Value\"}},\"Cantidad3\":{\"title\":\"Cantidad (3)\",\"type\":\"number\",\"format\":\"double\",\"x-ms-permission\":\"read-write\",\"x-ms-sort\":\"asc,desc\",\"x-ms-capabilities\":{\"filterFunctions\":[\"eq\",\"gt\",\"ge\",\"lt\",\"le\",\"ne\"]},\"maximum\":1.7976931348623157e+308,\"minimum\":-1.7976931348623157e+308},\"CilindrosPintados_x0028_1_x0029_#Id\":{\"title\":\"Cilindros Pintados [1] Id\",\"type\":\"integer\",\"format\":\"int64\",\"x-ms-permission\":\"read-only\",\"x-ms-visibility\":\"internal\"},\"CilindrosPintados_x0028_1_x0029_\":{\"title\":\"Cilindros Pintados [1]\",\"type\":\"object\",\"x-ms-permission\":\"read-write\",\"x-ms-sort\":\"asc,desc\",\"x-ms-capabilities\":{\"x-ms-sp\":{\"IsChoice\":true},\"filterFunctions\":[\"eq\"]},\"properties\":{\"@odata.type\":{\"title\":\"@odata.type\",\"x-ms-visibility\":\"internal\",\"type\":\"string\",\"x-ms-permission\":\"read-write\"},\"Value\":{\"title\":\"Value\",\"type\":\"string\",\"x-ms-dynamic-values\":{\"operationId\":\"GetEntityValues\",\"parameters\":{\"dataset\":{\"parameter\":\"dataset\"},\"table\":{\"parameter\":\"table\"},\"id\":\"5765ca88-13d1-47fe-87b0-9c5ad6990f15\"},\"value-path\":\"Value\",\"value-title\":\"Value\",\"value-collection\":\"value\"}},\"Id\":{\"title\":\"Id\",\"type\":\"integer\",\"format\":\"int64\",\"x-ms-visibility\":\"internal\",\"x-ms-permission\":\"read-only\"}},\"x-ms-displayFormat\":{\"titleProperty\":\"Value\"}},\"Cantidad_x005b_1_x005d_\":{\"title\":\"Cantidad [1]\",\"type\":\"number\",\"format\":\"double\",\"x-ms-permission\":\"read-write\",\"x-ms-sort\":\"asc,desc\",\"x-ms-capabilities\":{\"filterFunctions\":[\"eq\",\"gt\",\"ge\",\"lt\",\"le\",\"ne\"]},\"maximum\":1.7976931348623157e+308,\"minimum\":-1.7976931348623157e+308},\"CilindrosPintados_x005b_2_x005d_#Id\":{\"title\":\"Cilindros Pintados [2] Id\",\"type\":\"integer\",\"format\":\"int64\",\"x-ms-permission\":\"read-only\",\"x-ms-visibility\":\"internal\"},\"CilindrosPintados_x005b_2_x005d_\":{\"title\":\"Cilindros Pintados [2]\",\"type\":\"object\",\"x-ms-permission\":\"read-write\",\"x-ms-sort\":\"asc,desc\",\"x-ms-capabilities\":{\"x-ms-sp\":{\"IsChoice\":true},\"filterFunctions\":[\"eq\"]},\"properties\":{\"@odata.type\":{\"title\":\"@odata.type\",\"x-ms-visibility\":\"internal\",\"type\":\"string\",\"x-ms-permission\":\"read-write\"},\"Value\":{\"title\":\"Value\",\"type\":\"string\",\"x-ms-dynamic-values\":{\"operationId\":\"GetEntityValues\",\"parameters\":{\"dataset\":{\"parameter\":\"dataset\"},\"table\":{\"parameter\":\"table\"},\"id\":\"6b560aea-9493-4eac-8858-ef6e93912ff5\"},\"value-path\":\"Value\",\"value-title\":\"Value\",\"value-collection\":\"value\"}},\"Id\":{\"title\":\"Id\",\"type\":\"integer\",\"format\":\"int64\",\"x-ms-visibility\":\"internal\",\"x-ms-permission\":\"read-only\"}},\"x-ms-displayFormat\":{\"titleProperty\":\"Value\"}},\"Cantidad_x005b_2_x005d_\":{\"title\":\"Cantidad [2]\",\"type\":\"number\",\"format\":\"double\",\"x-ms-permission\":\"read-write\",\"x-ms-sort\":\"asc,desc\",\"x-ms-capabilities\":{\"filterFunctions\":[\"eq\",\"gt\",\"ge\",\"lt\",\"le\",\"ne\"]},\"maximum\":1.7976931348623157e+308,\"minimum\":-1.7976931348623157e+308},\"CilindrosPintados_x005b_3_x005d_#Id\":{\"title\":\"Cilindros Pintados [3] Id\",\"type\":\"integer\",\"format\":\"int64\",\"x-ms-permission\":\"read-only\",\"x-ms-visibility\":\"internal\"},\"CilindrosPintados_x005b_3_x005d_\":{\"title\":\"Cilindros Pintados [3]\",\"type\":\"object\",\"x-ms-permission\":\"read-write\",\"x-ms-sort\":\"asc,desc\",\"x-ms-capabilities\":{\"x-ms-sp\":{\"IsChoice\":true},\"filterFunctions\":[\"eq\"]},\"properties\":{\"@odata.type\":{\"title\":\"@odata.type\",\"x-ms-visibility\":\"internal\",\"type\":\"string\",\"x-ms-permission\":\"read-write\"},\"Value\":{\"title\":\"Value\",\"type\":\"string\",\"x-ms-dynamic-values\":{\"operationId\":\"GetEntityValues\",\"parameters\":{\"dataset\":{\"parameter\":\"dataset\"},\"table\":{\"parameter\":\"table\"},\"id\":\"ffd1cbbd-81f8-433b-8a18-1107343815e6\"},\"value-path\":\"Value\",\"value-title\":\"Value\",\"value-collection\":\"value\"}},\"Id\":{\"title\":\"Id\",\"type\":\"integer\",\"format\":\"int64\",\"x-ms-visibility\":\"internal\",\"x-ms-permission\":\"read-only\"}},\"x-ms-displayFormat\":{\"titleProperty\":\"Value\"}},\"Turno#Id\":{\"title\":\"Turno Id\",\"type\":\"integer\",\"format\":\"int64\",\"x-ms-permission\":\"read-only\",\"x-ms-visibility\":\"internal\"},\"Turno\":{\"title\":\"Turno\",\"type\":\"object\",\"x-ms-permission\":\"read-write\",\"x-ms-sort\":\"asc,desc\",\"x-ms-capabilities\":{\"x-ms-sp\":{\"IsChoice\":true},\"filterFunctions\":[\"eq\"]},\"properties\":{\"@odata.type\":{\"title\":\"@odata.type\",\"x-ms-visibility\":\"internal\",\"type\":\"string\",\"x-ms-permission\":\"read-write\"},\"Value\":{\"title\":\"Value\",\"type\":\"string\",\"x-ms-dynamic-values\":{\"operationId\":\"GetEntityValues\",\"parameters\":{\"dataset\":{\"parameter\":\"dataset\"},\"table\":{\"parameter\":\"table\"},\"id\":\"0a665766-9f73-4747-a322-7f08bc1d1e7c\"},\"value-path\":\"Value\",\"value-title\":\"Value\",\"value-collection\":\"value\"}},\"Id\":{\"title\":\"Id\",\"type\":\"integer\",\"format\":\"int64\",\"x-ms-visibility\":\"internal\",\"x-ms-permission\":\"read-only\"}},\"x-ms-displayFormat\":{\"titleProperty\":\"Value\"}},\"Author#Claims\":{\"title\":\"Creado por Claims\",\"type\":\"string\",\"description\":\"Identificador interno para el usuario que creó este elemento.\",\"x-ms-permission\":\"read-only\",\"x-ms-visibility\":\"internal\"},\"Author\":{\"title\":\"Creado por\",\"description\":\"El usuario que creó este elemento.\",\"type\":\"object\",\"x-ms-permission\":\"read-only\",\"x-ms-sort\":\"asc,desc\",\"x-ms-capabilities\":{\"filterFunctions\":[\"eq\"]},\"properties\":{\"@odata.type\":{\"title\":\"@odata.type\",\"x-ms-visibility\":\"internal\",\"type\":\"string\",\"x-ms-permission\":\"read-only\"},\"Claims\":{\"title\":\"Claims\",\"type\":\"string\",\"description\":\"Identificador interno para el usuario que creó este elemento.\",\"x-ms-permission\":\"read-only\",\"x-ms-dynamic-values\":{\"operationId\":\"GetEntityValues\",\"parameters\":{\"dataset\":{\"parameter\":\"dataset\"},\"table\":{\"parameter\":\"table\"},\"id\":\"1df5e554-ec7e-46a6-901d-d85a3881cb18\"},\"value-path\":\"Claims\",\"value-title\":\"DisplayName\",\"value-collection\":\"value\"}},\"DisplayName\":{\"title\":\"DisplayName\",\"type\":\"string\",\"description\":\"El nombre del usuario que creó este elemento.\",\"x-ms-permission\":\"read-only\",\"x-ms-capabilities\":{\"x-ms-sp\":{\"OdataQueryName\":\"Title\"},\"filterFunctions\":[\"eq\",\"startswith\"]}},\"Email\":{\"title\":\"Email\",\"type\":\"string\",\"description\":\"Dirección de correo electrónico del usuario que creó este elemento.\",\"format\":\"email\",\"x-ms-permission\":\"read-only\",\"x-ms-capabilities\":{\"x-ms-sp\":{\"OdataQueryName\":\"EMail\"},\"filterFunctions\":[\"eq\",\"startswith\"]}},\"Picture\":{\"title\":\"Picture\",\"type\":\"string\",\"description\":\"Vincula a una imagen del usuario que creó este elemento.\",\"format\":\"uri\",\"x-ms-media-kind\":\"image\",\"x-ms-media-default-folder-path\":\"/sites/Rayogas/Op\",\"x-ms-media-base-url\":\"https://grouprayogas.sharepoint.com/sites/Rayogas/Op\",\"x-ms-permission\":\"read-only\"},\"Department\":{\"title\":\"Department\",\"type\":\"string\",\"description\":\"Nombre del departamento del usuario que creó este elemento.\",\"x-ms-permission\":\"read-only\"},\"JobTitle\":{\"title\":\"JobTitle\",\"type\":\"string\",\"description\":\"Cargo del usuario que creó este elemento.\",\"x-ms-permission\":\"read-only\"}},\"x-ms-displayFormat\":{\"titleProperty\":\"DisplayName\",\"subtitleProperty\":\"Email\",\"thumbnailProperty\":\"Picture\"}},\"Cantidad_x005b_3_x005d_\":{\"title\":\"Cantidad [3]\",\"type\":\"number\",\"format\":\"double\",\"x-ms-permission\":\"read-write\",\"x-ms-sort\":\"asc,desc\",\"x-ms-capabilities\":{\"filterFunctions\":[\"eq\",\"gt\",\"ge\",\"lt\",\"le\",\"ne\"]},\"maximum\":1.7976931348623157e+308,\"minimum\":-1.7976931348623157e+308},\"OData__ColorTag\":{\"title\":\"Etiqueta de color\",\"type\":\"string\",\"x-ms-permission\":\"read-only\",\"x-ms-sort\":\"asc,desc\",\"x-ms-capabilities\":{\"filterFunctions\":[\"eq\",\"startswith\"]},\"maxLength\":255},\"ComplianceAssetId\":{\"title\":\"Id. de activo de cumplimiento normativo\",\"type\":\"string\",\"x-ms-permission\":\"read-only\",\"x-ms-sort\":\"asc,desc\",\"x-ms-capabilities\":{\"filterFunctions\":[\"eq\",\"startswith\"]},\"maxLength\":255},\"Registr_x00f3_#Claims\":{\"title\":\"Registró Claims\",\"type\":\"string\",\"x-ms-permission\":\"read-only\",\"x-ms-visibility\":\"internal\"},\"Registr_x00f3_\":{\"title\":\"Registró\",\"type\":\"object\",\"x-ms-permission\":\"read-write\",\"x-ms-sort\":\"asc,desc\",\"x-ms-capabilities\":{\"filterFunctions\":[\"eq\"]},\"properties\":{\"@odata.type\":{\"title\":\"@odata.type\",\"x-ms-visibility\":\"internal\",\"type\":\"string\",\"x-ms-permission\":\"read-write\"},\"Claims\":{\"title\":\"Claims\",\"type\":\"string\",\"x-ms-dynamic-values\":{\"operationId\":\"GetEntityValues\",\"parameters\":{\"dataset\":{\"parameter\":\"dataset\"},\"table\":{\"parameter\":\"table\"},\"id\":\"a379e84f-3f3d-494a-af03-efcdbe0913ef\"},\"value-path\":\"Claims\",\"value-title\":\"DisplayName\",\"value-collection\":\"value\"}},\"DisplayName\":{\"title\":\"DisplayName\",\"type\":\"string\",\"x-ms-permission\":\"read-only\",\"x-ms-capabilities\":{\"x-ms-sp\":{\"OdataQueryName\":\"Title\"},\"filterFunctions\":[\"eq\",\"startswith\"]}},\"Email\":{\"title\":\"Email\",\"type\":\"string\",\"format\":\"email\",\"x-ms-permission\":\"read-only\",\"x-ms-capabilities\":{\"x-ms-sp\":{\"OdataQueryName\":\"EMail\"},\"filterFunctions\":[\"eq\",\"startswith\"]}},\"Picture\":{\"title\":\"Picture\",\"type\":\"string\",\"format\":\"uri\",\"x-ms-media-kind\":\"image\",\"x-ms-media-default-folder-path\":\"/sites/Rayogas/Op\",\"x-ms-media-base-url\":\"https://grouprayogas.sharepoint.com/sites/Rayogas/Op\",\"x-ms-permission\":\"read-only\"},\"Department\":{\"title\":\"Department\",\"type\":\"string\",\"x-ms-permission\":\"read-only\"},\"JobTitle\":{\"title\":\"JobTitle\",\"type\":\"string\",\"x-ms-permission\":\"read-only\"}},\"x-ms-displayFormat\":{\"titleProperty\":\"DisplayName\",\"subtitleProperty\":\"Email\",\"thumbnailProperty\":\"Picture\"}},\"Modified\":{\"title\":\"Modificado\",\"description\":\"Cuándo se cambió por última vez este elemento.\",\"type\":\"string\",\"format\":\"date-time\",\"x-ms-permission\":\"read-only\",\"x-ms-sort\":\"asc,desc\",\"x-ms-capabilities\":{\"filterFunctions\":[\"eq\",\"gt\",\"ge\",\"lt\",\"le\",\"ne\"]}},\"Created\":{\"title\":\"Creado\",\"description\":\"Cuando se creó este elemento.\",\"type\":\"string\",\"format\":\"date-time\",\"x-ms-permission\":\"read-only\",\"x-ms-sort\":\"asc,desc\",\"x-ms-capabilities\":{\"filterFunctions\":[\"eq\",\"gt\",\"ge\",\"lt\",\"le\",\"ne\"]}},\"Editor#Claims\":{\"title\":\"Modificado por Claims\",\"type\":\"string\",\"description\":\"Identificador interno para el último usuario que modificó este elemento.\",\"x-ms-permission\":\"read-only\",\"x-ms-visibility\":\"internal\"},\"Editor\":{\"title\":\"Modificado por\",\"description\":\"El último usuario que modificó este elemento.\",\"type\":\"object\",\"x-ms-permission\":\"read-only\",\"x-ms-sort\":\"asc,desc\",\"x-ms-capabilities\":{\"filterFunctions\":[\"eq\"]},\"properties\":{\"@odata.type\":{\"title\":\"@odata.type\",\"x-ms-visibility\":\"internal\",\"type\":\"string\",\"x-ms-permission\":\"read-only\"},\"Claims\":{\"title\":\"Claims\",\"type\":\"string\",\"description\":\"Identificador interno para el último usuario que modificó este elemento.\",\"x-ms-permission\":\"read-only\",\"x-ms-dynamic-values\":{\"operationId\":\"GetEntityValues\",\"parameters\":{\"dataset\":{\"parameter\":\"dataset\"},\"table\":{\"parameter\":\"table\"},\"id\":\"d31655d1-1d5b-4511-95a1-7a09e9b75bf2\"},\"value-path\":\"Claims\",\"value-title\":\"DisplayName\",\"value-collection\":\"value\"}},\"DisplayName\":{\"title\":\"DisplayName\",\"type\":\"string\",\"description\":\"El nombre del usuario que modificó por última vez este elemento.\",\"x-ms-permission\":\"read-only\",\"x-ms-capabilities\":{\"x-ms-sp\":{\"OdataQueryName\":\"Title\"},\"filterFunctions\":[\"eq\",\"startswith\"]}},\"Email\":{\"title\":\"Email\",\"type\":\"string\",\"description\":\"Dirección de correo electrónico del usuario que modificó por última vez este elemento.\",\"format\":\"email\",\"x-ms-permission\":\"read-only\",\"x-ms-capabilities\":{\"x-ms-sp\":{\"OdataQueryName\":\"EMail\"},\"filterFunctions\":[\"eq\",\"startswith\"]}},\"Picture\":{\"title\":\"Picture\",\"type\":\"string\",\"description\":\"Vincular a una imagen del usuario que modificó por última vez este elemento.\",\"format\":\"uri\",\"x-ms-media-kind\":\"image\",\"x-ms-media-default-folder-path\":\"/sites/Rayogas/Op\",\"x-ms-media-base-url\":\"https://grouprayogas.sharepoint.com/sites/Rayogas/Op\",\"x-ms-permission\":\"read-only\"},\"Department\":{\"title\":\"Department\",\"type\":\"string\",\"description\":\"Nombre del departamento del usuario que modificó por última vez este elemento.\",\"x-ms-permission\":\"read-only\"},\"JobTitle\":{\"title\":\"JobTitle\",\"type\":\"string\",\"description\":\"Cargo del usuario que modificó por última vez este elemento.\",\"x-ms-permission\":\"read-only\"}},\"x-ms-displayFormat\":{\"titleProperty\":\"DisplayName\",\"subtitleProperty\":\"Email\",\"thumbnailProperty\":\"Picture\"}},\"{Identifier}\":{\"title\":\"Identificador\",\"description\":\"Valor que se puede usar en las acciones relacionadas con el archivo para seleccionar un archivo.\",\"type\":\"string\",\"x-ms-permission\":\"read-only\",\"x-ms-sort\":\"none\"},\"{IsFolder}\":{\"title\":\"EsCarpeta\",\"description\":\"Es True cuando el elemento es una carpeta, False en caso contrario.\",\"type\":\"boolean\",\"x-ms-permission\":\"read-only\",\"x-ms-sort\":\"none\"},\"{Thumbnail}\":{\"title\":\"Miniatura\",\"description\":\"Dirección URL de las miniaturas del elemento en 3 tamaños diferentes, si está disponible.\",\"type\":\"object\",\"x-ms-permission\":\"read-only\",\"x-ms-sort\":\"none\",\"properties\":{\"@odata.type\":{\"title\":\"@odata.type\",\"x-ms-visibility\":\"internal\",\"type\":\"string\",\"x-ms-permission\":\"read-only\"},\"Small\":{\"title\":\"Small\",\"type\":\"string\",\"description\":\"Dirección URL de la miniatura pequeña y muy comprimida del elemento, si está disponible.\",\"x-ms-permission\":\"read-only\"},\"Medium\":{\"title\":\"Medium\",\"type\":\"string\",\"description\":\"Dirección URL de la miniatura de tamaño estándar del elemento, si está disponible.\",\"x-ms-permission\":\"read-only\"},\"Large\":{\"title\":\"Large\",\"type\":\"string\",\"description\":\"Dirección URL de la miniatura de mayor tamaño del elemento, si está disponible.\",\"x-ms-permission\":\"read-only\"}}},\"{Link}\":{\"title\":\"Vinculo al elemento\",\"description\":\"Vínculo que se puede usar para obtener el archivo o el elemento de lista. Solo las personas con permisos para el elemento podrán abrir el vínculo.\",\"type\":\"string\",\"x-ms-permission\":\"read-only\",\"x-ms-sort\":\"none\"},\"{Name}\":{\"title\":\"Nombre\",\"description\":\"Nombre de archivo del elemento en las bibliotecas de documentos, nombre para mostrar del elemento en las listas.\",\"type\":\"string\",\"x-ms-permission\":\"read-only\",\"x-ms-sort\":\"none\"},\"{FilenameWithExtension}\":{\"title\":\"Nombre de archivo con extensión\",\"description\":\"En el caso de las bibliotecas, devuelve el nombre de archivo con la extensión. En el caso de las listas, devuelve la propiedad de título.\",\"type\":\"string\",\"x-ms-permission\":\"read-only\",\"x-ms-sort\":\"none\"},\"{Path}\":{\"title\":\"Ruta de acceso a la carpeta\",\"description\":\"Ruta de acceso a la carpeta en la que está el elemento, en relación con la dirección del sitio.\",\"type\":\"string\",\"x-ms-permission\":\"read-only\",\"x-ms-sort\":\"none\"},\"{FullPath}\":{\"title\":\"Ruta de acceso completa\",\"description\":\"La ruta de acceso completa de un elemento o una carpeta o un archivo\",\"type\":\"string\",\"x-ms-permission\":\"read-only\",\"x-ms-sort\":\"none\"},\"{ModerationStatus}\":{\"title\":\"Estado de aprobación de contenido\",\"description\":\"El estado de aprobación del contenido. Puede ser uno de los siguientes: borrador, pendiente, aprobado o rechazado\",\"type\":\"string\",\"x-ms-permission\":\"read-only\",\"x-ms-sort\":\"none\"},\"{ModerationComment}\":{\"title\":\"Comentarios asociados con la aprobación de contenido de este elemento de lista\",\"description\":\"Comentarios asociados con la moderación del elemento de lista.\",\"type\":\"string\",\"x-ms-permission\":\"read-only\",\"x-ms-sort\":\"none\"},\"{ContentType}#Id\":{\"title\":\"Tipo de contenido Id\",\"type\":\"string\",\"x-ms-permission\":\"read-only\",\"x-ms-visibility\":\"internal\"},\"{ContentType}\":{\"title\":\"Tipo de contenido\",\"description\":\"Nombre del tipo de contenido del elemento.\",\"type\":\"object\",\"x-ms-permission\":\"read-write\",\"x-ms-sort\":\"none\",\"properties\":{\"@odata.type\":{\"title\":\"@odata.type\",\"x-ms-visibility\":\"internal\",\"type\":\"string\",\"x-ms-permission\":\"read-write\"},\"Id\":{\"title\":\"Id\",\"type\":\"string\",\"x-ms-dynamic-values\":{\"operationId\":\"GetEntityValues\",\"parameters\":{\"dataset\":{\"parameter\":\"dataset\"},\"table\":{\"parameter\":\"table\"},\"id\":\"4651e8f2-38c9-4ad0-8def-41f743f76f30\"},\"value-path\":\"Id\",\"value-title\":\"Name\",\"value-collection\":\"value\"}},\"Name\":{\"title\":\"Name\",\"type\":\"string\",\"x-ms-permission\":\"read-only\"}},\"x-ms-displayFormat\":{\"titleProperty\":\"Name\"}},\"{HasAttachments}\":{\"title\":\"Tiene datos adjuntos\",\"description\":\"Indica la presencia de datos adjuntos en el elemento.\",\"type\":\"boolean\",\"x-ms-permission\":\"read-only\",\"x-ms-sort\":\"none\"},\"{Attachments}@odata.type\":{\"title\":\"{Attachments}\",\"type\":\"string\",\"x-ms-visibility\":\"internal\",\"x-ms-permission\":\"read-write\"},\"{Attachments}\":{\"title\":\"Datos adjuntos\",\"description\":\"Nunca devuelve ningún dato. Utilice puntos de conexión de datos adjuntos para obtener acceso a los datos adjuntos del elemento.\",\"x-ms-permission\":\"read-write\",\"targetEntity\":\"attachments\",\"format\":\"x-ms-containedMediaEntity\",\"x-ms-visibility\":\"internal\",\"type\":\"array\",\"items\":{\"type\":\"object\",\"format\":\"x-ms-mediaEntity\",\"x-ms-sort\":\"none\",\"properties\":{\"@odata.type\":{\"title\":\"@odata.type\",\"x-ms-visibility\":\"internal\",\"type\":\"string\",\"x-ms-permission\":\"read-write\"},\"Id\":{\"title\":\"Id\",\"type\":\"string\",\"x-ms-keyType\":\"primary\",\"x-ms-keyOrder\":1,\"x-ms-permission\":\"read-only\"},\"AbsoluteUri\":{\"title\":\"AbsoluteUri\",\"type\":\"string\",\"format\":\"uri\",\"x-ms-permission\":\"read-only\"},\"DisplayName\":{\"title\":\"DisplayName\",\"type\":\"string\",\"x-ms-permission\":\"read-only\"}}},\"@odata.type\":\"#Collection(Microsoft.Azure.Connectors.SharePoint.SPListItemAttachment)\"},\"{VersionNumber}\":{\"title\":\"Número de versión\",\"description\":\"Número de versión del archivo o el elemento de la lista.\",\"type\":\"string\",\"x-ms-permission\":\"read-only\",\"x-ms-sort\":\"none\"},\"{TriggerWindowStartToken}\":{\"title\":\"Token de inicio de ventana de desencadenador\",\"description\":\"Un token que expresa la hora de la última comprobación del flujo. Utilice esta información si desea comprobar si se han modificado una o más columnas desde la última comprobación del flujo.\",\"type\":\"string\",\"x-ms-permission\":\"read-only\",\"x-ms-sort\":\"none\"},\"{TriggerWindowEndToken}\":{\"title\":\"Token de fin de ventana de desencadenador\",\"description\":\"Un token que expresa la hora de la comprobación actual del flujo. Utilice esta información si desea comprobar si se han modificado una o más columnas desde la última comprobación del flujo.\",\"type\":\"string\",\"x-ms-permission\":\"read-only\",\"x-ms-sort\":\"none\"}},\"x-ms-relationships\":{\"Registr_x00f3__x003a_\":{\"targetEntity\":\"Registr_x00f3__x003a_\",\"referentialConstraints\":{\"Registr_x00f3__x003a_#Id\":{\"referencedProperty\":\"Id\"}}},\"Cargo\":{\"targetEntity\":\"Cargo\",\"referentialConstraints\":{\"Cargo#Id\":{\"referencedProperty\":\"Id\"}}},\"CENTROOPERACION\":{\"targetEntity\":\"CENTROOPERACION\",\"referentialConstraints\":{\"CENTROOPERACION#Id\":{\"referencedProperty\":\"Id\"}}},\"CilindrosLavados\":{\"targetEntity\":\"CilindrosLavados\",\"referentialConstraints\":{\"CilindrosLavados#Id\":{\"referencedProperty\":\"Id\"}}},\"CilindrosLavados2\":{\"targetEntity\":\"CilindrosLavados2\",\"referentialConstraints\":{\"CilindrosLavados2#Id\":{\"referencedProperty\":\"Id\"}}},\"Cilindroslavados3\":{\"targetEntity\":\"Cilindroslavados3\",\"referentialConstraints\":{\"Cilindroslavados3#Id\":{\"referencedProperty\":\"Id\"}}},\"CilindrosPintados_x0028_1_x0029_\":{\"targetEntity\":\"CilindrosPintados_x0028_1_x0029_\",\"referentialConstraints\":{\"CilindrosPintados_x0028_1_x0029_#Id\":{\"referencedProperty\":\"Id\"}}},\"CilindrosPintados_x005b_2_x005d_\":{\"targetEntity\":\"CilindrosPintados_x005b_2_x005d_\",\"referentialConstraints\":{\"CilindrosPintados_x005b_2_x005d_#Id\":{\"referencedProperty\":\"Id\"}}},\"CilindrosPintados_x005b_3_x005d_\":{\"targetEntity\":\"CilindrosPintados_x005b_3_x005d_\",\"referentialConstraints\":{\"CilindrosPintados_x005b_3_x005d_#Id\":{\"referencedProperty\":\"Id\"}}},\"Turno\":{\"targetEntity\":\"Turno\",\"referentialConstraints\":{\"Turno#Id\":{\"referencedProperty\":\"Id\"}}},\"Author\":{\"targetEntity\":\"Author\",\"referentialConstraints\":{\"Author#Claims\":{\"referencedProperty\":\"Claims\"}}},\"Registr_x00f3_\":{\"targetEntity\":\"Registr_x00f3_\",\"referentialConstraints\":{\"Registr_x00f3_#Claims\":{\"referencedProperty\":\"Claims\"}}},\"Editor\":{\"targetEntity\":\"Editor\",\"referentialConstraints\":{\"Editor#Claims\":{\"referencedProperty\":\"Claims\"}}},\"{ContentType}\":{\"targetEntity\":\"4651e8f2-38c9-4ad0-8def-41f743f76f30\",\"referentialConstraints\":{\"{ContentType}#Id\":{\"referencedProperty\":\"Id\"}}}},\"x-ms-displayFormat\":{\"propertiesDisplayOrder\":[\"Registr_x00f3__x003a_\",\"Cargo\",\"CENTROOPERACION\",\"FechaCreacion\",\"CilindrosLavados\",\"Cantidad\",\"CilindrosLavados2\",\"Cantidad2\",\"Cilindroslavados3\",\"Cantidad3\",\"CilindrosPintados_x0028_1_x0029_\",\"Cantidad_x005b_1_x005d_\",\"Turno\",\"CilindrosPintados_x005b_2_x005d_\",\"Cantidad_x005b_2_x005d_\",\"CilindrosPintados_x005b_3_x005d_\",\"Cantidad_x005b_3_x005d_\",\"{Attachments}\"],\"propertiesCompactDisplayOrder\":[\"Title\",\"Registr_x00f3__x003a_\",\"Cargo\",\"CENTROOPERACION\",\"FechaCreacion\",\"CilindrosLavados\",\"Cantidad\",\"CilindrosLavados2\",\"Cantidad2\",\"Cilindroslavados3\",\"Cantidad3\",\"CilindrosPintados_x0028_1_x0029_\",\"Cantidad_x005b_1_x005d_\",\"CilindrosPintados_x005b_2_x005d_\",\"Cantidad_x005b_2_x005d_\",\"CilindrosPintados_x005b_3_x005d_\",\"Turno\",\"Author\",\"Cantidad_x005b_3_x005d_\"],\"propertiesTabularDisplayOrder\":[\"Title\",\"Registr_x00f3__x003a_\",\"Cargo\",\"CENTROOPERACION\",\"FechaCreacion\",\"CilindrosLavados\",\"Cantidad\",\"CilindrosLavados2\",\"Cantidad2\",\"Cilindroslavados3\",\"Cantidad3\",\"CilindrosPintados_x0028_1_x0029_\",\"Cantidad_x005b_1_x005d_\",\"CilindrosPintados_x005b_2_x005d_\",\"Cantidad_x005b_2_x005d_\",\"CilindrosPintados_x005b_3_x005d_\",\"Turno\",\"Author\",\"Cantidad_x005b_3_x005d_\"]}}},\"referencedEntities\":{\"Registr_x00f3__x003a_\":{\"lookupEndpoint\":{\"path\":\"/tables/b6645f33-1a17-4858-9c14-16cc8efe49df/entities/Registr_x00f3__x003a_\",\"capabilities\":{\"searchable\":true,\"requiresSearch\":false}}},\"Cargo\":{\"lookupEndpoint\":{\"path\":\"/tables/b6645f33-1a17-4858-9c14-16cc8efe49df/entities/Cargo\",\"capabilities\":{\"searchable\":true,\"requiresSearch\":false}}},\"CENTROOPERACION\":{\"lookupEndpoint\":{\"path\":\"/tables/b6645f33-1a17-4858-9c14-16cc8efe49df/entities/CENTROOPERACION\",\"capabilities\":{\"searchable\":true,\"requiresSearch\":false}}},\"CilindrosLavados\":{\"lookupEndpoint\":{\"path\":\"/tables/b6645f33-1a17-4858-9c14-16cc8efe49df/entities/CilindrosLavados\",\"capabilities\":{\"searchable\":true,\"requiresSearch\":false}}},\"CilindrosLavados2\":{\"lookupEndpoint\":{\"path\":\"/tables/b6645f33-1a17-4858-9c14-16cc8efe49df/entities/CilindrosLavados2\",\"capabilities\":{\"searchable\":true,\"requiresSearch\":false}}},\"Cilindroslavados3\":{\"lookupEndpoint\":{\"path\":\"/tables/b6645f33-1a17-4858-9c14-16cc8efe49df/entities/Cilindroslavados3\",\"capabilities\":{\"searchable\":true,\"requiresSearch\":false}}},\"CilindrosPintados_x0028_1_x0029_\":{\"lookupEndpoint\":{\"path\":\"/tables/b6645f33-1a17-4858-9c14-16cc8efe49df/entities/CilindrosPintados_x0028_1_x0029_\",\"capabilities\":{\"searchable\":true,\"requiresSearch\":false}}},\"CilindrosPintados_x005b_2_x005d_\":{\"lookupEndpoint\":{\"path\":\"/tables/b6645f33-1a17-4858-9c14-16cc8efe49df/entities/CilindrosPintados_x005b_2_x005d_\",\"capabilities\":{\"searchable\":true,\"requiresSearch\":false}}},\"CilindrosPintados_x005b_3_x005d_\":{\"lookupEndpoint\":{\"path\":\"/tables/b6645f33-1a17-4858-9c14-16cc8efe49df/entities/CilindrosPintados_x005b_3_x005d_\",\"capabilities\":{\"searchable\":true,\"requiresSearch\":false}}},\"Turno\":{\"lookupEndpoint\":{\"path\":\"/tables/b6645f33-1a17-4858-9c14-16cc8efe49df/entities/Turno\",\"capabilities\":{\"searchable\":true,\"requiresSearch\":false}}},\"Author\":{\"lookupEndpoint\":{\"path\":\"/tables/b6645f33-1a17-4858-9c14-16cc8efe49df/entities/Author\",\"capabilities\":{\"searchable\":true,\"requiresSearch\":false}}},\"Registr_x00f3_\":{\"lookupEndpoint\":{\"path\":\"/tables/b6645f33-1a17-4858-9c14-16cc8efe49df/entities/Registr_x00f3_\",\"capabilities\":{\"searchable\":true,\"requiresSearch\":false}}},\"Editor\":{\"lookupEndpoint\":{\"path\":\"/tables/b6645f33-1a17-4858-9c14-16cc8efe49df/entities/Editor\",\"capabilities\":{\"searchable\":true,\"requiresSearch\":false}}},\"4651e8f2-38c9-4ad0-8def-41f743f76f30\":{\"lookupEndpoint\":{\"path\":\"/tables/b6645f33-1a17-4858-9c14-16cc8efe49df/entities/%257bContentType%257d\",\"capabilities\":{\"searchable\":true,\"requiresSearch\":false}}}},\"webUrl\":\"https://grouprayogas.sharepoint.com/sites/Rayogas/Op/Lists/Inventario Mantenimiento Cilindros/AllItems.aspx\"}"
  },
  "EntityName": "InventarioMantenimientoCilindros",
  "TableName": "b6645f33-1a17-4858-9c14-16cc8efe49df"
}